Metadata-Version: 2.1
Name: odoo-addon-account_payment_mode_brand
Version: 18.0.1.0.0.5
Requires-Python: >=3.10
Requires-Dist: odoo-addon-account_brand==18.0.*
Requires-Dist: odoo-addon-account_payment_partner==18.0.*
Requires-Dist: odoo-addon-base_view_inheritance_extension==18.0.*
Requires-Dist: odoo-addon-brand==18.0.*
Requires-Dist: odoo==18.0.*
Summary: This addon define allowed payment mode per brand
Home-page: https://github.com/OCA/brand
License: AGPL-3
Author: ACSONE SA/NV,Odoo Community Association (OCA)
Author-email: support@odoo-community.org
Classifier: Programming Language :: Python
Classifier: Framework :: Odoo
Classifier: Framework :: Odoo :: 18.0
Classifier: License :: OSI Approved :: GNU Affero General Public License v3
